rtsf/__about__.py
rtsf/__init__.py
rtsf/p_applog.py
rtsf/p_common.py
rtsf/p_compat.py
rtsf/p_exception.py
rtsf/p_executer.py
rtsf/p_report.py
rtsf/p_testcase.py
rtsf/p_tracer.py
rtsf/templates/default_report_template.html
rtsf-3.0.2.dist-info/LICENSE
rtsf-3.0.2.dist-info/METADATA
rtsf-3.0.2.dist-info/WHEEL
rtsf-3.0.2.dist-info/top_level.txt
rtsf-3.0.2.dist-info/RECORD
