Metadata-Version: 2.1
Name: rtsf
Version: 3.0.2
Summary: a test service framework
Home-page: https://github.com/RockFeng0/rtsf
Author: RockFeng0
Author-email: 281589463@qq.com
License: MIT
Keywords: test requests locust HTTP api selenium appium uiautomation
Platform: UNKNOWN
Requires-Python: >=2.7, !=3.0.*, !=3.1.*, !=3.2.*, !=3.3.*, <4
Requires-Dist: PyYAML
Requires-Dist: Jinja2
Requires-Dist: colorama
Requires-Dist: colorlog
Requires-Dist: urllib3
